privacy_sherlock/__init__.py
privacy_sherlock/app.py
privacy_sherlock/classification/__init__.py
privacy_sherlock/classification/classify_pii.py
privacy_sherlock/detection/__init__.py
privacy_sherlock/detection/presidio_helpers.py
privacy_sherlock/detection/regex_pii_detection.py
privacy_sherlock/ingestion/__init__.py
privacy_sherlock/ingestion/directory_ingestion.py
privacy_sherlock/ingestion/mongo_ingestion.py
privacy_sherlock/ingestion/mysql_ingestion.py
privacy_sherlock/ingestion/s3_ingestion.py
privacy_sherlock/ingestion/sqlretrieve.py
privacy_sherlock/ingestion/sqltest.py
privacy_sherlock/risk_assessment/__init__.py
privacy_sherlock/risk_assessment/risk_score.py
privacy_sherlock/visualization/__init__.py
privacy_sherlock/visualization/plot_pii_distribution.py
PrivacySherlock-0.0.1.dist-info/LICENSE
PrivacySherlock-0.0.1.dist-info/METADATA
PrivacySherlock-0.0.1.dist-info/WHEEL
PrivacySherlock-0.0.1.dist-info/top_level.txt
PrivacySherlock-0.0.1.dist-info/RECORD
